{
    "id": "https://contrataciondelestado.es/sindicacion/licitacionesPerfilContratante/1542692",
    "link": {
        "@href": "https://contrataciondelestado.es/wps/poc?uri=deeplink:detalle_licitacion&idEvl=xkmRr9Nk36YQK2TEfXGy%2BA%3D%3D"
    },
    "summary": {
        "@type": "text",
        "#text": "Id licitaci\u00f3n: 10007 17 0031 00; \u00d3rgano de Contrataci\u00f3n: Jefatura de Administraci\u00f3n Econ\u00f3mica del Cuarto Militar de S.M. el Rey y Guardia Real; Importe: 70289.25 EUR; Estado: RES"
    },
    "title": "Adquisici\u00f3n material talleres Cia., Apoyo a Instalaciones de la Guardia Real",
    "updated": "2017-07-05T10:22:03.669+02:00",
    "cac-place-ext:ContractFolderStatus": {
        "cbc:ContractFolderID": "10007 17 0031 00",
        "cbc-place-ext:ContractFolderStatusCode": {
            "@languageID": "es",
            "@listURI": "https://contrataciondelestado.es/codice/cl/2.04/SyndicationContractFolderStatusCode-2.04.gc",
            "#text": "RES"
        },
        "cac-place-ext:LocatedContractingParty": {
            "cbc:ContractingPartyTypeCode": {
                "@listURI": "http://contrataciondelestado.es/codice/cl/1.04/ContractingAuthorityCode-1.04.gc",
                "#text": "1"
            },
            "cac:Party": {
                "cac:PartyIdentification": {
                    "cbc:ID": {
                        "@schemeName": "DIR3",
                        "#text": "EA0002973"
                    }
                },
                "cac:PartyName": {
                    "cbc:Name": "Jefatura de Administraci\u00f3n Econ\u00f3mica del Cuarto Militar de S.M. el Rey y Guardia Real"
                },
                "cac:PostalAddress": {
                    "cbc:CityName": "El Pardo (Madrid)",
                    "cbc:PostalZone": "28048",
                    "cac:AddressLine": {
                        "cbc:Line": "Paseo del Pardo s/n"
                    },
                    "cac:Country": {
                        "cbc:IdentificationCode": {
                            "@listURI": "http://docs.oasis-open.org/ubl/os-ubl-2.0/cl/gc/default/CountryIdentificationCode-2.0.gc",
                            "#text": "ES"
                        },
                        "cbc:Name": "Espa\u00f1a"
                    }
                },
                "cac:Contact": {
                    "cbc:Name": "Jefatura de Administraci\u00f3n Econ\u00f3mica del Cuarto Militar de S.M. el Rey y Guardia Real",
                    "cbc:Telephone": "917407010",
                    "cbc:Telefax": "917407046",
                    "cbc:ElectronicMail": "contrataciongr@mde.es"
                }
            }
        },
        "cac:ProcurementProject": {
            "cbc:Name": "Adquisici\u00f3n material talleres Cia., Apoyo a Instalaciones de la Guardia Real",
            "cbc:TypeCode": {
                "@listURI": "http://contrataciondelestado.es/codice/cl/2.02/ContractCode-2.02.gc",
                "#text": "1"
            },
            "cbc:SubTypeCode": {
                "@listURI": "http://contrataciondelestado.es/codice/cl/1.04/GoodsContractCode-1.04.gc",
                "#text": "2"
            },
            "cac:BudgetAmount": {
                "cbc:TotalAmount": {
                    "@currencyID": "EUR",
                    "#text": "85050"
                },
                "cbc:TaxExclusiveAmount": {
                    "@currencyID": "EUR",
                    "#text": "70289.25"
                }
            },
            "cac:RequiredCommodityClassification": [
                {
                    "cbc:ItemClassificationCode": {
                        "@listURI": "http://contrataciondelestado.es/codice/cl/1.04/CPV2007-1.04.gc",
                        "#text": "03419100"
                    }
                },
                {
                    "cbc:ItemClassificationCode": {
                        "@listURI": "http://contrataciondelestado.es/codice/cl/1.04/CPV2007-1.04.gc",
                        "#text": "16160000"
                    }
                },
                {
                    "cbc:ItemClassificationCode": {
                        "@listURI": "http://contrataciondelestado.es/codice/cl/1.04/CPV2007-1.04.gc",
                        "#text": "44110000"
                    }
                },
                {
                    "cbc:ItemClassificationCode": {
                        "@listURI": "http://contrataciondelestado.es/codice/cl/1.04/CPV2007-1.04.gc",
                        "#text": "44800000"
                    }
                },
                {
                    "cbc:ItemClassificationCode": {
                        "@listURI": "http://contrataciondelestado.es/codice/cl/1.04/CPV2007-1.04.gc",
                        "#text": "44300000"
                    }
                },
                {
                    "cbc:ItemClassificationCode": {
                        "@listURI": "http://contrataciondelestado.es/codice/cl/1.04/CPV2007-1.04.gc",
                        "#text": "42130000"
                    }
                },
                {
                    "cbc:ItemClassificationCode": {
                        "@listURI": "http://contrataciondelestado.es/codice/cl/1.04/CPV2007-1.04.gc",
                        "#text": "44500000"
                    }
                }
            ],
            "cac:RealizedLocation": {
                "cbc:CountrySubentity": "Madrid",
                "cbc:CountrySubentityCode": {
                    "@listURI": "http://contrataciondelestado.es/codice/cl/2.06/NUTS-2016.gc",
                    "#text": "ES300"
                },
                "cac:Address": {
                    "cac:Country": {
                        "cbc:IdentificationCode": {
                            "@listURI": "http://docs.oasis-open.org/ubl/os-ubl-2.0/cl/gc/default/CountryIdentificationCode-2.0.gc",
                            "#text": "ES"
                        },
                        "cbc:Name": "Espa\u00f1a"
                    }
                }
            },
            "cac:PlannedPeriod": {
                "cbc:DurationMeasure": {
                    "@unitCode": "ANN",
                    "#text": "1"
                }
            }
        },
        "cac:ProcurementProjectLot": [
            {
                "cbc:ID": {
                    "@schemeName": "ID_LOTE",
                    "#text": "1"
                },
                "cac:ProcurementProject": {
                    "cbc:Name": "Alba\u00f1iler\u00eda, fontaner\u00eda, carpinter\u00eda, cristaler\u00eda y cerrajer\u00eda",
                    "cac:BudgetAmount": {
                        "cbc:TotalAmount": {
                            "@currencyID": "EUR",
                            "#text": "25050"
                        },
                        "cbc:TaxExclusiveAmount": {
                            "@currencyID": "EUR",
                            "#text": "20702.48"
                        }
                    },
                    "cac:RequiredCommodityClassification": [
                        {
                            "cbc:ItemClassificationCode": {
                                "@listURI": "http://contrataciondelestado.es/codice/cl/1.04/CPV2007-1.04.gc",
                                "#text": "44500000"
                            }
                        },
                        {
                            "cbc:ItemClassificationCode": {
                                "@listURI": "http://contrataciondelestado.es/codice/cl/1.04/CPV2007-1.04.gc",
                                "#text": "44300000"
                            }
                        },
                        {
                            "cbc:ItemClassificationCode": {
                                "@listURI": "http://contrataciondelestado.es/codice/cl/1.04/CPV2007-1.04.gc",
                                "#text": "44110000"
                            }
                        },
                        {
                            "cbc:ItemClassificationCode": {
                                "@listURI": "http://contrataciondelestado.es/codice/cl/1.04/CPV2007-1.04.gc",
                                "#text": "42130000"
                            }
                        },
                        {
                            "cbc:ItemClassificationCode": {
                                "@listURI": "http://contrataciondelestado.es/codice/cl/1.04/CPV2007-1.04.gc",
                                "#text": "16160000"
                            }
                        },
                        {
                            "cbc:ItemClassificationCode": {
                                "@listURI": "http://contrataciondelestado.es/codice/cl/1.04/CPV2007-1.04.gc",
                                "#text": "03419100"
                            }
                        },
                        {
                            "cbc:ItemClassificationCode": {
                                "@listURI": "http://contrataciondelestado.es/codice/cl/1.04/CPV2007-1.04.gc",
                                "#text": "44800000"
                            }
                        }
                    ]
                }
            },
            {
                "cbc:ID": {
                    "@schemeName": "ID_LOTE",
                    "#text": "2"
                },
                "cac:ProcurementProject": {
                    "cbc:Name": "Ferreter\u00eda, herramientas, riego y jardines",
                    "cac:BudgetAmount": {
                        "cbc:TotalAmount": {
                            "@currencyID": "EUR",
                            "#text": "20000"
                        },
                        "cbc:TaxExclusiveAmount": {
                            "@currencyID": "EUR",
                            "#text": "16528.93"
                        }
                    },
                    "cac:RequiredCommodityClassification": [
                        {
                            "cbc:ItemClassificationCode": {
                                "@listURI": "http://contrataciondelestado.es/codice/cl/1.04/CPV2007-1.04.gc",
                                "#text": "44500000"
                            }
                        },
                        {
                            "cbc:ItemClassificationCode": {
                                "@listURI": "http://contrataciondelestado.es/codice/cl/1.04/CPV2007-1.04.gc",
                                "#text": "44300000"
                            }
                        },
                        {
                            "cbc:ItemClassificationCode": {
                                "@listURI": "http://contrataciondelestado.es/codice/cl/1.04/CPV2007-1.04.gc",
                                "#text": "44110000"
                            }
                        },
                        {
                            "cbc:ItemClassificationCode": {
                                "@listURI": "http://contrataciondelestado.es/codice/cl/1.04/CPV2007-1.04.gc",
                                "#text": "42130000"
                            }
                        },
                        {
                            "cbc:ItemClassificationCode": {
                                "@listURI": "http://contrataciondelestado.es/codice/cl/1.04/CPV2007-1.04.gc",
                                "#text": "16160000"
                            }
                        },
                        {
                            "cbc:ItemClassificationCode": {
                                "@listURI": "http://contrataciondelestado.es/codice/cl/1.04/CPV2007-1.04.gc",
                                "#text": "03419100"
                            }
                        },
                        {
                            "cbc:ItemClassificationCode": {
                                "@listURI": "http://contrataciondelestado.es/codice/cl/1.04/CPV2007-1.04.gc",
                                "#text": "44800000"
                            }
                        }
                    ]
                }
            },
            {
                "cbc:ID": {
                    "@schemeName": "ID_LOTE",
                    "#text": "3"
                },
                "cac:ProcurementProject": {
                    "cbc:Name": "Instalaciones el\u00e9ctricas",
                    "cac:BudgetAmount": {
                        "cbc:TotalAmount": {
                            "@currencyID": "EUR",
                            "#text": "21000"
                        },
                        "cbc:TaxExclusiveAmount": {
                            "@currencyID": "EUR",
                            "#text": "17355.37"
                        }
                    },
                    "cac:RequiredCommodityClassification": [
                        {
                            "cbc:ItemClassificationCode": {
                                "@listURI": "http://contrataciondelestado.es/codice/cl/1.04/CPV2007-1.04.gc",
                                "#text": "03419100"
                            }
                        },
                        {
                            "cbc:ItemClassificationCode": {
                                "@listURI": "http://contrataciondelestado.es/codice/cl/1.04/CPV2007-1.04.gc",
                                "#text": "16160000"
                            }
                        },
                        {
                            "cbc:ItemClassificationCode": {
                                "@listURI": "http://contrataciondelestado.es/codice/cl/1.04/CPV2007-1.04.gc",
                                "#text": "42130000"
                            }
                        },
                        {
                            "cbc:ItemClassificationCode": {
                                "@listURI": "http://contrataciondelestado.es/codice/cl/1.04/CPV2007-1.04.gc",
                                "#text": "44110000"
                            }
                        },
                        {
                            "cbc:ItemClassificationCode": {
                                "@listURI": "http://contrataciondelestado.es/codice/cl/1.04/CPV2007-1.04.gc",
                                "#text": "44300000"
                            }
                        },
                        {
                            "cbc:ItemClassificationCode": {
                                "@listURI": "http://contrataciondelestado.es/codice/cl/1.04/CPV2007-1.04.gc",
                                "#text": "44500000"
                            }
                        },
                        {
                            "cbc:ItemClassificationCode": {
                                "@listURI": "http://contrataciondelestado.es/codice/cl/1.04/CPV2007-1.04.gc",
                                "#text": "44800000"
                            }
                        }
                    ]
                }
            },
            {
                "cbc:ID": {
                    "@schemeName": "ID_LOTE",
                    "#text": "4"
                },
                "cac:ProcurementProject": {
                    "cbc:Name": "Pintura",
                    "cac:BudgetAmount": {
                        "cbc:TotalAmount": {
                            "@currencyID": "EUR",
                            "#text": "19000"
                        },
                        "cbc:TaxExclusiveAmount": {
                            "@currencyID": "EUR",
                            "#text": "15702.25"
                        }
                    },
                    "cac:RequiredCommodityClassification": [
                        {
                            "cbc:ItemClassificationCode": {
                                "@listURI": "http://contrataciondelestado.es/codice/cl/1.04/CPV2007-1.04.gc",
                                "#text": "03419100"
                            }
                        },
                        {
                            "cbc:ItemClassificationCode": {
                                "@listURI": "http://contrataciondelestado.es/codice/cl/1.04/CPV2007-1.04.gc",
                                "#text": "16160000"
                            }
                        },
                        {
                            "cbc:ItemClassificationCode": {
                                "@listURI": "http://contrataciondelestado.es/codice/cl/1.04/CPV2007-1.04.gc",
                                "#text": "42130000"
                            }
                        },
                        {
                            "cbc:ItemClassificationCode": {
                                "@listURI": "http://contrataciondelestado.es/codice/cl/1.04/CPV2007-1.04.gc",
                                "#text": "44110000"
                            }
                        },
                        {
                            "cbc:ItemClassificationCode": {
                                "@listURI": "http://contrataciondelestado.es/codice/cl/1.04/CPV2007-1.04.gc",
                                "#text": "44300000"
                            }
                        },
                        {
                            "cbc:ItemClassificationCode": {
                                "@listURI": "http://contrataciondelestado.es/codice/cl/1.04/CPV2007-1.04.gc",
                                "#text": "44500000"
                            }
                        },
                        {
                            "cbc:ItemClassificationCode": {
                                "@listURI": "http://contrataciondelestado.es/codice/cl/1.04/CPV2007-1.04.gc",
                                "#text": "44800000"
                            }
                        }
                    ]
                }
            }
        ],
        "cac:TenderResult": [
            {
                "cbc:ResultCode": {
                    "@listURI": "http://contrataciondelestado.es/codice/cl/2.02/TenderResultCode-2.02.gc",
                    "#text": "8"
                },
                "cbc:Description": "Ser la oferta m\u00e1s ventajosa",
                "cbc:AwardDate": "2017-06-23",
                "cbc:ReceivedTenderQuantity": "2",
                "cbc:StartDate": "2017-09-01",
                "cac:Contract": {
                    "cbc:ID": "10007 17 0031 01",
                    "cbc:IssueDate": "2017-07-04"
                },
                "cac:WinningParty": {
                    "cac:PartyIdentification": {
                        "cbc:ID": {
                            "@schemeName": "NIF",
                            "#text": "A78601549"
                        }
                    },
                    "cac:PartyName": {
                        "cbc:Name": "V. CORONADO E HIJOS"
                    }
                },
                "cac:AwardedTenderedProject": {
                    "cbc:ProcurementProjectLotID": "1",
                    "cac:LegalMonetaryTotal": {
                        "cbc:TaxExclusiveAmount": {
                            "@currencyID": "EUR",
                            "#text": "20702.48"
                        },
                        "cbc:PayableAmount": {
                            "@currencyID": "EUR",
                            "#text": "25050"
                        }
                    }
                }
            },
            {
                "cbc:ResultCode": {
                    "@listURI": "http://contrataciondelestado.es/codice/cl/2.02/TenderResultCode-2.02.gc",
                    "#text": "8"
                },
                "cbc:Description": "Ser la oferta m\u00e1s ventajosa",
                "cbc:AwardDate": "2017-06-23",
                "cbc:ReceivedTenderQuantity": "3",
                "cbc:StartDate": "2017-09-01",
                "cac:Contract": {
                    "cbc:ID": "10007 17 0031 02",
                    "cbc:IssueDate": "2017-07-04"
                },
                "cac:WinningParty": {
                    "cac:PartyIdentification": {
                        "cbc:ID": {
                            "@schemeName": "NIF",
                            "#text": "A78601549"
                        }
                    },
                    "cac:PartyName": {
                        "cbc:Name": "V. CORONADO E HIJOS"
                    }
                },
                "cac:AwardedTenderedProject": {
                    "cbc:ProcurementProjectLotID": "2",
                    "cac:LegalMonetaryTotal": {
                        "cbc:TaxExclusiveAmount": {
                            "@currencyID": "EUR",
                            "#text": "16528.92"
                        },
                        "cbc:PayableAmount": {
                            "@currencyID": "EUR",
                            "#text": "20000"
                        }
                    }
                }
            },
            {
                "cbc:ResultCode": {
                    "@listURI": "http://contrataciondelestado.es/codice/cl/2.02/TenderResultCode-2.02.gc",
                    "#text": "8"
                },
                "cbc:Description": "Ser la oferta m\u00e1s ventajosa",
                "cbc:AwardDate": "2017-06-23",
                "cbc:ReceivedTenderQuantity": "4",
                "cbc:StartDate": "2017-09-01",
                "cac:Contract": {
                    "cbc:ID": "10007 17 0031 03",
                    "cbc:IssueDate": "2017-07-03"
                },
                "cac:WinningParty": {
                    "cac:PartyIdentification": {
                        "cbc:ID": {
                            "@schemeName": "NIF",
                            "#text": "B83234799"
                        }
                    },
                    "cac:PartyName": {
                        "cbc:Name": "FERRETERIA FERAYU, S.L"
                    }
                },
                "cac:AwardedTenderedProject": {
                    "cbc:ProcurementProjectLotID": "3",
                    "cac:LegalMonetaryTotal": {
                        "cbc:TaxExclusiveAmount": {
                            "@currencyID": "EUR",
                            "#text": "17355.37"
                        },
                        "cbc:PayableAmount": {
                            "@currencyID": "EUR",
                            "#text": "21000"
                        }
                    }
                }
            },
            {
                "cbc:ResultCode": {
                    "@listURI": "http://contrataciondelestado.es/codice/cl/2.02/TenderResultCode-2.02.gc",
                    "#text": "8"
                },
                "cbc:Description": "Ser la oferta m\u00e1s ventajosa",
                "cbc:AwardDate": "2017-06-23",
                "cbc:ReceivedTenderQuantity": "4",
                "cbc:StartDate": "2017-09-01",
                "cac:Contract": {
                    "cbc:ID": "10007 17 0031 04",
                    "cbc:IssueDate": "2017-07-03"
                },
                "cac:WinningParty": {
                    "cac:PartyIdentification": {
                        "cbc:ID": {
                            "@schemeName": "NIF",
                            "#text": "B83234799"
                        }
                    },
                    "cac:PartyName": {
                        "cbc:Name": "FERRETERIA FERAYU, S.L"
                    }
                },
                "cac:AwardedTenderedProject": {
                    "cbc:ProcurementProjectLotID": "4",
                    "cac:LegalMonetaryTotal": {
                        "cbc:TaxExclusiveAmount": {
                            "@currencyID": "EUR",
                            "#text": "15702.47"
                        },
                        "cbc:PayableAmount": {
                            "@currencyID": "EUR",
                            "#text": "19000"
                        }
                    }
                }
            }
        ],
        "cac:TenderingTerms": {
            "cbc:RequiredCurriculaIndicator": "false",
            "cac:RequiredFinancialGuarantee": {
                "cbc:GuaranteeTypeCode": {
                    "@listURI": "http://contrataciondelestado.es/codice/cl/1.04/GuaranteeTypeCode-1.04.gc",
                    "#text": "2"
                },
                "cbc:AmountRate": "5"
            },
            "cac:TendererQualificationRequest": {
                "cac:TechnicalEvaluationCriteria": {
                    "cbc:EvaluationCriteriaTypeCode": {
                        "@listURI": "http://contrataciondelestado.es/codice/cl/2.0/TechnicalCapabilityTypeCode-2.0.gc",
                        "#text": "XSX-CERTCALIDAD"
                    },
                    "cbc:Description": "Seg\u00fan cl\u00e1usula 17 del PCAP"
                },
                "cac:FinancialEvaluationCriteria": {
                    "cbc:EvaluationCriteriaTypeCode": {
                        "@listURI": "http://contrataciondelestado.es/codice/cl/2.0/FinancialCapabilityTypeCode-2.0.gc",
                        "#text": "5"
                    },
                    "cbc:Description": "Seg\u00fan cl\u00e1usula 16 del PCAP"
                },
                "cac:SpecificTendererRequirement": [
                    {
                        "cbc:RequirementTypeCode": {
                            "@listURI": "http://contrataciondelestado.es/codice/cl/2.0/DeclarationTypeCode-2.0.gc",
                            "#text": "1"
                        }
                    },
                    {
                        "cbc:RequirementTypeCode": {
                            "@listURI": "http://contrataciondelestado.es/codice/cl/2.0/DeclarationTypeCode-2.0.gc",
                            "#text": "2"
                        }
                    }
                ]
            },
            "cac:Language": {
                "cbc:ID": "es"
            }
        },
        "cac:TenderingProcess": {
            "cbc:ProcedureCode": {
                "@listURI": "https://contrataciondelestado.es/codice/cl/2.04/SyndicationTenderingProcessCode-2.04.gc",
                "#text": "1"
            },
            "cbc:UrgencyCode": {
                "@listURI": "http://contrataciondelestado.es/codice/cl/1.04/DiligenceTypeCode-1.04.gc",
                "#text": "1"
            },
            "cac:DocumentAvailabilityPeriod": {
                "cbc:EndDate": "2017-05-19",
                "cbc:EndTime": "09:00:00"
            },
            "cac:TenderSubmissionDeadlinePeriod": {
                "cbc:EndDate": "2017-05-22",
                "cbc:EndTime": "12:00:00"
            }
        },
        "cac:LegalDocumentReference": {
            "cbc:ID": "PCAP Material talleres Apoyo a Instalaciones.pdf",
            "cac:Attachment": {
                "cac:ExternalReference": {
                    "cbc:URI": "https://contrataciondelestado.es/wps/wcm/connect/PLACE_es/Site/area/docAccCmpnt?srv=cmpnt&cmpntname=GetDocumentsById&source=library&DocumentIdParam=771b1a92-568a-4d17-98ca-c9c8f421ace1",
                    "cbc:DocumentHash": "as3Zt3SoctA14TLDV7ponH30EK4="
                }
            }
        },
        "cac:TechnicalDocumentReference": {
            "cbc:ID": "PPT Material talleres Apoyo a Instalaciones.pdf",
            "cac:Attachment": {
                "cac:ExternalReference": {
                    "cbc:URI": "https://contrataciondelestado.es/wps/wcm/connect/PLACE_es/Site/area/docAccCmpnt?srv=cmpnt&cmpntname=GetDocumentsById&source=library&DocumentIdParam=8092b1ae-5392-4ecd-b7c9-ff9b2563c869",
                    "cbc:DocumentHash": "bQG1PDqi4lf8zO4bUcEdfL/bDdQ="
                }
            }
        },
        "cac:AdditionalDocumentReference": {
            "cbc:ID": "408-17 Anexo VI Bis PCAP.xlsx",
            "cac:Attachment": {
                "cac:ExternalReference": {
                    "cbc:URI": "https://contrataciondelestado.es/wps/wcm/connect/PLACE_es/Site/area/docAccCmpnt?srv=cmpnt&cmpntname=GetDocumentsById&source=library&DocumentIdParam=a11f3d0e-8624-427f-915a-68d8df15fc7b",
                    "cbc:DocumentHash": "zzFIv9PRnpbKO/uu06bNeTL84Oo="
                }
            }
        },
        "cac-place-ext:ValidNoticeInfo": [
            {
                "cbc-place-ext:NoticeTypeCode": {
                    "@listURI": "http://contrataciondelestado.es/codice/cl/2.04/TenderingNoticeTypeCode-2.04.gc",
                    "#text": "DOC_CN"
                },
                "cac-place-ext:AdditionalPublicationStatus": {
                    "cbc-place-ext:PublicationMediaName": "BOE",
                    "cac-place-ext:AdditionalPublicationDocumentReference": {
                        "cbc:IssueDate": "2017-04-29"
                    }
                }
            },
            {
                "cbc-place-ext:NoticeTypeCode": {
                    "@listURI": "http://contrataciondelestado.es/codice/cl/2.04/TenderingNoticeTypeCode-2.04.gc",
                    "#text": "DOC_CAN_ADJ"
                },
                "cac-place-ext:AdditionalPublicationStatus": {
                    "cbc-place-ext:PublicationMediaName": "Perfil del Contratante",
                    "cac-place-ext:AdditionalPublicationDocumentReference": {
                        "cbc:IssueDate": "2017-07-05"
                    }
                }
            },
            {
                "cbc-place-ext:NoticeTypeCode": {
                    "@listURI": "http://contrataciondelestado.es/codice/cl/2.04/TenderingNoticeTypeCode-2.04.gc",
                    "#text": "DOC_CD"
                },
                "cac-place-ext:AdditionalPublicationStatus": {
                    "cbc-place-ext:PublicationMediaName": "Perfil del Contratante",
                    "cac-place-ext:AdditionalPublicationDocumentReference": [
                        {
                            "cbc:IssueDate": "2017-04-28"
                        },
                        {
                            "cbc:IssueDate": "2017-05-08"
                        }
                    ]
                }
            },
            {
                "cbc-place-ext:NoticeTypeCode": {
                    "@listURI": "http://contrataciondelestado.es/codice/cl/2.04/TenderingNoticeTypeCode-2.04.gc",
                    "#text": "DOC_CN"
                },
                "cac-place-ext:AdditionalPublicationStatus": {
                    "cbc-place-ext:PublicationMediaName": "Perfil del Contratante",
                    "cac-place-ext:AdditionalPublicationDocumentReference": {
                        "cbc:IssueDate": "2017-04-26"
                    }
                }
            },
            {
                "cbc-place-ext:NoticeTypeCode": {
                    "@listURI": "http://contrataciondelestado.es/codice/cl/2.04/TenderingNoticeTypeCode-2.04.gc",
                    "#text": "DOC_FORM"
                },
                "cac-place-ext:AdditionalPublicationStatus": {
                    "cbc-place-ext:PublicationMediaName": "Perfil del Contratante",
                    "cac-place-ext:AdditionalPublicationDocumentReference": {
                        "cbc:IssueDate": "2017-07-05"
                    }
                }
            }
        ]
    }
}