{
    "datosbasicos__numero_expediente": "CONTR 2018 0000024478",
    "estado_expediente__estado": "Resuelta (Formalizado)",
    "apertura_ofertas": {
        "lugar": [
            "DELEGACION DEL GOBIERNO EN ALMERIA",
            "ARAPILES 10-12 04001 (ALMERIA Espana)",
            "Fecha Apertura del sobre de criterios de adjudicacion evaluables por aplicacion de formulas : 13/06/2018 a las 09:00 horas"
        ]
    },
    "referencias_diarios_oficiales": [],
    "estado_expediente__fecha_adjudicacion": "22/06/2018",
    "importes__importe_licitacion_(sin_iva)": "151.510,61EUR",
    "datosbasicos__titulo_expediente": "SERVICIO DE LIMPIEZA DE LAS DISTINTAS DEPENDENCIAS DE LA DELEGACION DEL GOB",
    "importes__importe_licitacion_(con_iva)": "183.327,84EUR",
    "estado_expediente__notas": [
        "27/07/2018 12:17 - Formalizacion",
        "Actualizado: Formalizacion"
    ],
    "documentacion_complementaria": [
        {
            "descripcion": "PCAP def 31-05-2018 (PDF) (947.14Kb)",
            "link": "http://www.juntadeandalucia.es/contratacion/document/download?refCode=2018-0000020236&refDoc=2018-0000020236-2",
            "numero_expediente": "CONTR 2018 0000024478"
        },
        {
            "descripcion": "Pliego de prescripciones t\u00e9cnicas (PDF) (300.82Kb)",
            "link": "http://www.juntadeandalucia.es/contratacion/document/download?refCode=2018-0000020236&refDoc=2018-0000020236-1",
            "numero_expediente": "CONTR 2018 0000024478"
        },
        {
            "descripcion": "Nota informativa pliegos (PDF) (112.7Kb)",
            "link": "http://www.juntadeandalucia.es/contratacion/document/download?refCode=2018-0000020236&refDoc=2018-0000020236-8",
            "numero_expediente": "CONTR 2018 0000024478"
        },
        {
            "descripcion": "Pliego de cl\u00e1usulas administrativas particulares (PDF) (525.12Kb)",
            "link": "http://www.juntadeandalucia.es/contratacion/document/download?refCode=2018-0000020236&refDoc=2018-0000020236-5",
            "numero_expediente": "CONTR 2018 0000024478"
        },
        {
            "descripcion": "Contrato formalizado (PDF) (625.08Kb)",
            "link": "http://www.juntadeandalucia.es/contratacion/document/download?refCode=2018-0000026116&refDoc=2018-0000026116-0",
            "numero_expediente": "CONTR 2018 0000024478"
        },
        {
            "descripcion": "Resoluci\u00f3n de adjudicaci\u00f3n (PDF) (211.55Kb)",
            "link": "http://www.juntadeandalucia.es/contratacion/document/download?refCode=2018-0000021069&refDoc=2018-0000021069-1",
            "numero_expediente": "CONTR 2018 0000024478"
        },
        {
            "descripcion": "Designaci\u00f3n composici\u00f3n de la Mesa (PDF) (291.49Kb)",
            "link": "http://www.juntadeandalucia.es/contratacion/document/download?refCode=2018-0000020236&refDoc=2018-0000020236-4",
            "numero_expediente": "CONTR 2018 0000024478"
        },
        {
            "descripcion": "Memoria justificativa (PDF) (166.92Kb)",
            "link": "http://www.juntadeandalucia.es/contratacion/document/download?refCode=2018-0000020236&refDoc=2018-0000020236-6",
            "numero_expediente": "CONTR 2018 0000024478"
        },
        {
            "descripcion": "Resoluci\u00f3n de aprobaci\u00f3n del expediente (PDF) (122.81Kb)",
            "link": "http://www.juntadeandalucia.es/contratacion/document/download?refCode=2018-0000020236&refDoc=2018-0000020236-7",
            "numero_expediente": "CONTR 2018 0000024478"
        },
        {
            "descripcion": "Resoluc suplencia mesa 14-06-2018 (PDF) (157.58Kb)",
            "link": "http://www.juntadeandalucia.es/contratacion/document/download?refCode=2018-0000020236&refDoc=2018-0000020236-10",
            "numero_expediente": "CONTR 2018 0000024478"
        },
        {
            "descripcion": "Acta mesa apertura sobre aplicaci\u00f3n de f\u00f3rmulas (PDF) (365.27Kb)",
            "link": "http://www.juntadeandalucia.es/contratacion/document/download?refCode=2018-0000020236&refDoc=2018-0000020236-11",
            "numero_expediente": "CONTR 2018 0000024478"
        },
        {
            "descripcion": "Acta examen doc previa a la adjudicaci\u00f3n (PDF) (109.54Kb)",
            "link": "http://www.juntadeandalucia.es/contratacion/document/download?refCode=2018-0000021069&refDoc=2018-0000021069-0",
            "numero_expediente": "CONTR 2018 0000024478"
        },
        {
            "descripcion": "Acta mesa calificaci\u00f3n administrativa (PDF) (71.11Kb)",
            "link": "http://www.juntadeandalucia.es/contratacion/document/download?refCode=2018-0000020236&refDoc=2018-0000020236-9",
            "numero_expediente": "CONTR 2018 0000024478"
        }
    ],
    "anuncios_publicados": [
        {
            "descripcion": "01/06/2018 14:24, 2018-0000018761-Convocatoria de licitaci\u00f3n",
            "anuncio_id": " 2018-0000018761",
            "anuncio_desc": "Convocatoria de licitaci\u00f3n",
            "link": "http://www.juntadeandalucia.es/haciendayadministracionpublica/apl/verifirmapdc/descargaInformeParametros?transaccion=BQ8SHOOtXtcGNB9PT%2F1fR84cenB071d7&tipoPie=4",
            "numero_expediente": "CONTR 2018 0000024478",
            "datetime": "2018-06-01T14:24:00+00:00"
        },
        {
            "descripcion": "11/06/2018 14:14, 2018-0000019680-Convocatoria de licitaci\u00f3n (Infor.Adicional)",
            "anuncio_id": " 2018-0000019680",
            "anuncio_desc": "Convocatoria de licitaci\u00f3n (Infor.Adicional)",
            "link": "http://www.juntadeandalucia.es/haciendayadministracionpublica/apl/verifirmapdc/descargaInformeParametros?transaccion=Obkz59N9p9BdDOu8vk1Y4yJqUCje%2B%2B1i&tipoPie=4",
            "numero_expediente": "CONTR 2018 0000024478",
            "datetime": "2018-06-11T14:14:00+00:00"
        },
        {
            "descripcion": "14/06/2018 11:49, 2018-0000020087-Convocatoria de licitaci\u00f3n (Infor.Adicional)",
            "anuncio_id": " 2018-0000020087",
            "anuncio_desc": "Convocatoria de licitaci\u00f3n (Infor.Adicional)",
            "link": "http://www.juntadeandalucia.es/haciendayadministracionpublica/apl/verifirmapdc/descargaInformeParametros?transaccion=G8gmOGn1u%2BKNrxp6G5lWQ6vJYER37PP1&tipoPie=4",
            "numero_expediente": "CONTR 2018 0000024478",
            "datetime": "2018-06-14T11:49:00+00:00"
        },
        {
            "descripcion": "15/06/2018 11:52, 2018-0000020236-Convocatoria de licitaci\u00f3n (Infor.Adicional)",
            "anuncio_id": " 2018-0000020236",
            "anuncio_desc": "Convocatoria de licitaci\u00f3n (Infor.Adicional)",
            "link": "http://www.juntadeandalucia.es/haciendayadministracionpublica/apl/verifirmapdc/descargaInformeParametros?transaccion=tm4CZvSLRRMtS%2FkXzA77YCJqUCje%2B%2B1i&tipoPie=4",
            "numero_expediente": "CONTR 2018 0000024478",
            "datetime": "2018-06-15T11:52:00+00:00"
        },
        {
            "descripcion": "22/06/2018 13:53, 2018-0000021069-Adjudicaci\u00f3n",
            "anuncio_id": " 2018-0000021069",
            "anuncio_desc": "Adjudicaci\u00f3n",
            "link": "http://www.juntadeandalucia.es/haciendayadministracionpublica/apl/verifirmapdc/descargaInformeParametros?transaccion=%2FJqV3TDxwEvQ1WW5YetgMyJqUCje%2B%2B1i&tipoPie=4",
            "numero_expediente": "CONTR 2018 0000024478",
            "datetime": "2018-06-22T13:53:00+00:00"
        },
        {
            "descripcion": "27/07/2018 12:17, 2018-0000026116-Formalizaci\u00f3n",
            "anuncio_id": " 2018-0000026116",
            "anuncio_desc": "Formalizaci\u00f3n",
            "link": "http://www.juntadeandalucia.es/haciendayadministracionpublica/apl/verifirmapdc/descargaInformeParametros?transaccion=Jvc6H8inaLeX5jEvpmrpFs4cenB071d7&tipoPie=4",
            "numero_expediente": "CONTR 2018 0000024478",
            "datetime": "2018-07-27T12:17:00+00:00"
        }
    ],
    "datosbasicos__organo_contratacion": "Delegacion del Gobierno de la Junta de Andalucia en Almeria",
    "estado_expediente__nif": "B04737474",
    "datosbasicos__division_por_lotes": "No",
    "importes__valor_estimado": "151.510,61EUR",
    "estado_expediente__fecha_la_formalizacion": "17/07/2018",
    "id": 75378,
    "datosbasicos__tipo_contrato": "Servicios",
    "importes__importe_adjudicacion_(sin_iva)": "148.757,85EUR",
    "secciones": {
        "documentacion_complementaria": 2,
        "anuncios_publicados": 9,
        "apertura_ofertas": 7,
        "referencias_diarios_oficiales": 8,
        "estado_expediente": 1,
        "presentacion_solicitudes": 5,
        "requisitos_criterios_condiciones": 4,
        "importes": 0,
        "presentacion_ofertas": 6,
        "obtencion_documentacion_informacion": 3
    },
    "datosbasicos__lugar_ejecucion_nuts": "ES611",
    "datosbasicos__tramitacion": "Urgencia",
    "importes__importe_adjudicacion_(con_iva)": "179.997,00EUR",
    "datosbasicos__duracion_contrato": "1 ano",
    "requisitos_criterios_condiciones": {
        "requisitos_minimos_contratista": "Los establecidos en el pliego de cl\u00e1usulas administrativas particulares",
        "criterios_adjudicacion": "Los establecidos en el pliego de cl\u00e1usulas administrativas particulares",
        "condiciones_especiales_adjudicacion_contrato": "Los establecidos en el pliego de cl\u00e1usulas administrativas particulares",
        "criterios_objetivos_para_la_seleccion_candidatos_el_procedimiento": "Los establecidos en el pliego de cl\u00e1usulas administrativas particulares"
    },
    "presentacion_ofertas__notas": [
        "ARAPILES 10-12 04001 (ALMERIA Espana)",
        "DELEGACION DEL GOBIERNO EN ALMERIA"
    ],
    "datosbasicos__lugar_tramitacion": "ALMERIA",
    "datosbasicos__procedimiento": "Abierto",
    "estado_expediente__no_licitadores": "5",
    "datosbasicos__lugar_ejecucion": "ALMERIA",
    "origen": {
        "terminos_uso": "http://www.juntadeandalucia.es/informacion/legal.html",
        "url": "http://www.juntadeandalucia.es/temas/contratacion-publica/perfiles-licitaciones/detalle/000000075378.html"
    },
    "estado_expediente__adjudicatario": "FAMIM 1.997, S.L.",
    "datosbasicos__descripcion": "SERVICIO DE LIMPIEZA DE LAS DISTINTAS DEPENDENCIAS DE LA DELEGACION DEL GOBIERNO EN ALMERIA",
    "datosbasicos__clasificacion_cpv": "90919200 Servicios de limpieza de oficinas",
    "obtencion_documentacion_informacion": {
        "fecha_limite_obtencion": "09/06/2018 a las 14:00 horas",
        "puntos_contacto": [
            "Jose Morata Gutierrez",
            "950002116",
            "950002095",
            "jose.morata@juntadeandalucia.es",
            "http://juntadeandalucia.es/temas/contratacion-publica/perfiles-licitaciones.html"
        ],
        "lugar": [
            "DELEGACION DEL GOBIERNO EN ALMERIA",
            "ARAPILES 10-12 04001 (ALMERIA Espana)"
        ]
    },
    "presentacion_ofertas__fecha_limite_presentacion_ofertas": "09/06/2018 a las 14:00 horas"
}