{
    "id": "https://contrataciondelestado.es/sindicacion/licitacionesPerfilContratante/946174",
    "link": {
        "@href": "https://contrataciondelestado.es/wps/poc?uri=deeplink:detalle_licitacion&idEvl=ilfTh24l3fIQK2TEfXGy%2BA%3D%3D"
    },
    "summary": {
        "@type": "text",
        "#text": "Id licitaci\u00f3n: 2/16; \u00d3rgano de Contrataci\u00f3n: Direcci\u00f3n Provincial del Servicio P\u00fablico de Empleo Estatal en Madrid; Importe: 49586.78 EUR; Estado: RES"
    },
    "title": "Contrataci\u00f3n del servicio de recogida y transporte de paqueter\u00eda y documentaci\u00f3n entre la Direcci\u00f3n Provincial del SEPE de Madrid y sus diferentes unidades administrativas.",
    "updated": "2015-12-23T14:26:46.361+01:00",
    "cac-place-ext:ContractFolderStatus": {
        "cbc:ContractFolderID": "2/16",
        "cbc-place-ext:ContractFolderStatusCode": {
            "@languageID": "es",
            "@listURI": "https://contrataciondelestado.es/codice/cl/2.04/SyndicationContractFolderStatusCode-2.04.gc",
            "#text": "RES"
        },
        "cac-place-ext:LocatedContractingParty": {
            "cbc:ContractingPartyTypeCode": {
                "@listURI": "http://contrataciondelestado.es/codice/cl/1.04/ContractingAuthorityCode-1.04.gc",
                "#text": "1"
            },
            "cac:Party": {
                "cbc:WebsiteURI": "http://sede.sepe.gob.es",
                "cac:PartyIdentification": {
                    "cbc:ID": {
                        "@schemeName": "DIR3",
                        "#text": "E03697904"
                    }
                },
                "cac:PartyName": {
                    "cbc:Name": "Direcci\u00f3n Provincial del Servicio P\u00fablico de Empleo Estatal en Madrid"
                },
                "cac:PostalAddress": {
                    "cbc:CityName": "Madrid",
                    "cbc:PostalZone": "28016",
                    "cac:AddressLine": {
                        "cbc:Line": "Victor de la Serna, 43"
                    },
                    "cac:Country": {
                        "cbc:IdentificationCode": {
                            "@listURI": "http://docs.oasis-open.org/ubl/os-ubl-2.0/cl/gc/default/CountryIdentificationCode-2.0.gc",
                            "#text": "ES"
                        },
                        "cbc:Name": "Espa\u00f1a"
                    }
                },
                "cac:Contact": {
                    "cbc:Name": "Direcci\u00f3n Provincial del Servicio P\u00fablico de Empleo Estatal en Madrid",
                    "cbc:Telephone": "913533564",
                    "cbc:Telefax": "913533555",
                    "cbc:ElectronicMail": "dp28patrimonio@sepe.es"
                }
            }
        },
        "cac:ProcurementProject": {
            "cbc:Name": "Contrataci\u00f3n del servicio de recogida y transporte de paqueter\u00eda y documentaci\u00f3n entre la Direcci\u00f3n Provincial del SEPE de Madrid y sus diferentes unidades administrativas.",
            "cbc:TypeCode": {
                "@listURI": "http://contrataciondelestado.es/codice/cl/2.02/ContractCode-2.02.gc",
                "#text": "2"
            },
            "cbc:SubTypeCode": {
                "@listURI": "http://contrataciondelestado.es/codice/cl/1.04/WorksContractCode-1.04.gc",
                "#text": "20"
            },
            "cac:BudgetAmount": {
                "cbc:EstimatedOverallContractAmount": {
                    "@currencyID": "EUR",
                    "#text": "99173.56"
                },
                "cbc:TotalAmount": {
                    "@currencyID": "EUR",
                    "#text": "60000"
                },
                "cbc:TaxExclusiveAmount": {
                    "@currencyID": "EUR",
                    "#text": "49586.78"
                }
            },
            "cac:RequiredCommodityClassification": {
                "cbc:ItemClassificationCode": {
                    "@listURI": "http://contrataciondelestado.es/codice/cl/1.04/CPV2007-1.04.gc",
                    "#text": "63710000"
                }
            },
            "cac:RealizedLocation": {
                "cbc:CountrySubentity": "ESPA\u00d1A",
                "cbc:CountrySubentityCode": {
                    "@listURI": "http://contrataciondelestado.es/codice/cl/2.0/NUTS-2009.gc",
                    "#text": "ES"
                },
                "cac:Address": {
                    "cac:Country": {
                        "cbc:IdentificationCode": {
                            "@listURI": "http://docs.oasis-open.org/ubl/os-ubl-2.0/cl/gc/default/CountryIdentificationCode-2.0.gc",
                            "#text": "ES"
                        },
                        "cbc:Name": "Espa\u00f1a"
                    }
                }
            },
            "cac:PlannedPeriod": {
                "cbc:DurationMeasure": {
                    "@unitCode": "ANN",
                    "#text": "1"
                }
            },
            "cac:ContractExtension": {
                "cbc:OptionsDescription": "Posibilidad de pr\u00f3rrogas"
            }
        },
        "cac:TenderResult": {
            "cbc:ResultCode": {
                "@listURI": "http://contrataciondelestado.es/codice/cl/2.02/TenderResultCode-2.02.gc",
                "#text": "8"
            },
            "cbc:Description": "Se adjudica la segunda oferta econ\u00f3mica m\u00e1s baja por renuncia de la primera oferta m\u00e1s baja",
            "cbc:AwardDate": "2015-12-02",
            "cbc:ReceivedTenderQuantity": "6",
            "cbc:StartDate": "2016-01-01",
            "cac:Contract": {
                "cbc:ID": "02/16",
                "cbc:IssueDate": "2015-12-22"
            },
            "cac:WinningParty": {
                "cac:PartyIdentification": {
                    "cbc:ID": {
                        "@schemeName": "NIF",
                        "#text": "A80920077"
                    }
                },
                "cac:PartyName": {
                    "cbc:Name": "MENSYTRANS,S.A."
                }
            },
            "cac:AwardedTenderedProject": {
                "cac:LegalMonetaryTotal": {
                    "cbc:TaxExclusiveAmount": {
                        "@currencyID": "EUR",
                        "#text": "32978.16"
                    },
                    "cbc:PayableAmount": {
                        "@currencyID": "EUR",
                        "#text": "39903.57"
                    }
                }
            }
        },
        "cac:TenderingTerms": {
            "cbc:VariantConstraintIndicator": "false",
            "cac:RequiredFinancialGuarantee": {
                "cbc:GuaranteeTypeCode": {
                    "@listURI": "http://contrataciondelestado.es/codice/cl/1.04/GuaranteeTypeCode-1.04.gc",
                    "#text": "2"
                },
                "cbc:AmountRate": "5"
            },
            "cac:TendererQualificationRequest": {
                "cac:TechnicalEvaluationCriteria": {
                    "cbc:EvaluationCriteriaTypeCode": {
                        "@listURI": "http://contrataciondelestado.es/codice/cl/2.0/TechnicalCapabilityTypeCode-2.0.gc",
                        "#text": "ZZZ"
                    },
                    "cbc:Description": "Ver punto 4.2 del PCAP. p\u00e1g.11"
                },
                "cac:FinancialEvaluationCriteria": {
                    "cbc:EvaluationCriteriaTypeCode": {
                        "@listURI": "http://contrataciondelestado.es/codice/cl/2.0/TechnicalCapabilityTypeCode-2.0.gc",
                        "#text": "5"
                    },
                    "cbc:Description": "Ver punto 4.1 del PCAP. p\u00e1g. 11"
                }
            },
            "cac:Language": {
                "cbc:ID": "es"
            }
        },
        "cac:TenderingProcess": {
            "cbc:ProcedureCode": {
                "@listURI": "https://contrataciondelestado.es/codice/cl/2.04/SyndicationTenderingProcessCode-2.04.gc",
                "#text": "1"
            },
            "cbc:UrgencyCode": {
                "@listURI": "http://contrataciondelestado.es/codice/cl/1.04/DiligenceTypeCode-1.04.gc",
                "#text": "1"
            },
            "cac:DocumentAvailabilityPeriod": {
                "cbc:EndDate": "2015-11-13",
                "cbc:EndTime": "10:00:00"
            },
            "cac:TenderSubmissionDeadlinePeriod": {
                "cbc:EndDate": "2015-11-13",
                "cbc:EndTime": "10:00:00"
            }
        },
        "cac:LegalDocumentReference": {
            "cbc:ID": "PCASACA.pdf",
            "cac:Attachment": {
                "cac:ExternalReference": {
                    "cbc:URI": "https://contrataciondelestado.es/wps/wcm/connect/PLACE_es/Site/area/docAccCmpnt?srv=cmpnt&cmpntname=GetDocumentsById&source=library&DocumentIdParam=0d54f3b9-1bf0-4b2e-8c38-d72de9e9517c",
                    "cbc:DocumentHash": "K1h5841ZNWJoB8UBPCRuG1lo6mg="
                }
            }
        },
        "cac:TechnicalDocumentReference": {
            "cbc:ID": "PPTSACAS.pdf",
            "cac:Attachment": {
                "cac:ExternalReference": {
                    "cbc:URI": "https://contrataciondelestado.es/wps/wcm/connect/PLACE_es/Site/area/docAccCmpnt?srv=cmpnt&cmpntname=GetDocumentsById&source=library&DocumentIdParam=b5b6e0a5-e50f-4abd-83a5-926f7695a455",
                    "cbc:DocumentHash": "ICn6lmbzh2rCYuaWI1fNBwcjUsU="
                }
            }
        },
        "cac-place-ext:ValidNoticeInfo": [
            {
                "cbc-place-ext:NoticeTypeCode": {
                    "@listURI": "http://contrataciondelestado.es/codice/cl/2.04/TenderingNoticeTypeCode-2.04.gc",
                    "#text": "DOC_CN"
                },
                "cac-place-ext:AdditionalPublicationStatus": {
                    "cbc-place-ext:PublicationMediaName": "BOE",
                    "cac-place-ext:AdditionalPublicationDocumentReference": {
                        "cbc:IssueDate": "2015-10-15"
                    }
                }
            },
            {
                "cbc-place-ext:NoticeTypeCode": {
                    "@listURI": "http://contrataciondelestado.es/codice/cl/2.04/TenderingNoticeTypeCode-2.04.gc",
                    "#text": "DOC_CAN_ADJ"
                },
                "cac-place-ext:AdditionalPublicationStatus": {
                    "cbc-place-ext:PublicationMediaName": "Perfil del Contratante",
                    "cac-place-ext:AdditionalPublicationDocumentReference": {
                        "cbc:IssueDate": "2015-12-18"
                    }
                }
            },
            {
                "cbc-place-ext:NoticeTypeCode": {
                    "@listURI": "http://contrataciondelestado.es/codice/cl/2.04/TenderingNoticeTypeCode-2.04.gc",
                    "#text": "DOC_CD"
                },
                "cac-place-ext:AdditionalPublicationStatus": {
                    "cbc-place-ext:PublicationMediaName": "Perfil del Contratante",
                    "cac-place-ext:AdditionalPublicationDocumentReference": {
                        "cbc:IssueDate": "2015-10-16"
                    }
                }
            },
            {
                "cbc-place-ext:NoticeTypeCode": {
                    "@listURI": "http://contrataciondelestado.es/codice/cl/2.04/TenderingNoticeTypeCode-2.04.gc",
                    "#text": "DOC_CN"
                },
                "cac-place-ext:AdditionalPublicationStatus": {
                    "cbc-place-ext:PublicationMediaName": "Perfil del Contratante",
                    "cac-place-ext:AdditionalPublicationDocumentReference": {
                        "cbc:IssueDate": "2015-10-16"
                    }
                }
            },
            {
                "cbc-place-ext:NoticeTypeCode": {
                    "@listURI": "http://contrataciondelestado.es/codice/cl/2.04/TenderingNoticeTypeCode-2.04.gc",
                    "#text": "DOC_FORM"
                },
                "cac-place-ext:AdditionalPublicationStatus": {
                    "cbc-place-ext:PublicationMediaName": "Perfil del Contratante",
                    "cac-place-ext:AdditionalPublicationDocumentReference": {
                        "cbc:IssueDate": "2015-12-23"
                    }
                }
            },
            {
                "cbc-place-ext:NoticeTypeCode": {
                    "@listURI": "http://contrataciondelestado.es/codice/cl/2.04/TenderingNoticeTypeCode-2.04.gc",
                    "#text": "DOC_PIN"
                },
                "cac-place-ext:AdditionalPublicationStatus": {
                    "cbc-place-ext:PublicationMediaName": "Perfil del Contratante",
                    "cac-place-ext:AdditionalPublicationDocumentReference": {
                        "cbc:IssueDate": "2015-10-16"
                    }
                }
            }
        ]
    }
}