{
    "id": "https://contrataciondelestado.es/sindicacion/PlataformasAgregadasSinMenores/1961903",
    "link": {
        "@href": "https://contractaciopublica.gencat.cat/ecofin_pscp/AppJava/awardnotice.pscp?reqCode=viewDcan&idDoc=17160381&lawType=2"
    },
    "summary": {
        "@type": "text",
        "#text": "Id licitaci\u00f3n: AA/EIA/CONTRACTACI\u00d3/2013/28. SEGONA PR\u00d2RROGA; Estado: RESUELTA;"
    },
    "title": "SEGONA PR\u00d2RROGA del contracte administratiu de serveis de connexi\u00f3 a Internet mitjan\u00e7ant una l\u00ednia de fibra \u00f2ptica de 1 GB sim\u00e8tric per l'Ajuntament de Viladecans.",
    "updated": "2016-07-29T15:10:46.040+02:00",
    "cac-place-ext:ContractFolderStatus": {
        "cbc:ContractFolderID": "AA/EIA/CONTRACTACI\u00d3/2013/28. SEGONA PR\u00d2RROGA",
        "cbc-place-ext:ContractFolderStatusCode": {
            "@languageID": "es",
            "@listURI": "https://contrataciondelestado.es/codice/cl/2.04/SyndicationContractFolderStatusCode-2.04.gc",
            "#text": "RES"
        },
        "cac-place-ext:LocatedContractingParty": {
            "cac:Party": {
                "cac:PartyName": {
                    "cbc:Name": "Ajuntament de Viladecans"
                }
            },
            "cac-place-ext:ParentLocatedParty": {
                "cac:PartyName": {
                    "cbc:Name": "Entitats municipals de Catalunya"
                },
                "cac-place-ext:ParentLocatedParty": null
            }
        },
        "cac:ProcurementProject": {
            "cbc:Name": "SEGONA PR\u00d2RROGA del contracte administratiu de serveis de connexi\u00f3 a Internet mitjan\u00e7ant una l\u00ednia de fibra \u00f2ptica de 1 GB sim\u00e8tric per l'Ajuntament de Viladecans.",
            "cbc:TypeCode": {
                "@listURI": "http://contrataciondelestado.es/codice/cl/2.02/ContractCode-2.02.gc",
                "#text": "2"
            },
            "cac:BudgetAmount": {
                "cbc:EstimatedOverallContractAmount": {
                    "@currencyID": "EUR",
                    "#text": "32000"
                },
                "cbc:TaxExclusiveAmount": {
                    "@currencyID": "EUR",
                    "#text": "16000"
                }
            },
            "cac:RequiredCommodityClassification": {
                "cbc:ItemClassificationCode": {
                    "@listURI": "http://contrataciondelestado.es/codice/cl/1.04/CPV2007-1.04.gc",
                    "#text": "72400000"
                }
            },
            "cac:RealizedLocation": {
                "cbc:CountrySubentityCode": {
                    "@listURI": "http://contrataciondelestado.es/codice/cl/2.06/NUTS-2016.gc",
                    "#text": "ES511"
                }
            },
            "cac:PlannedPeriod": {
                "cbc:StartDate": "2016-05-01",
                "cbc:EndDate": "2017-04-30"
            }
        },
        "cac:TenderResult": {
            "cbc:ResultCode": {
                "@listURI": "http://contrataciondelestado.es/codice/cl/2.02/TenderResultCode-2.02.gc",
                "#text": "9"
            },
            "cbc:ReceivedTenderQuantity": "1",
            "cac:WinningParty": {
                "cac:PartyIdentification": {
                    "cbc:ID": {
                        "@schemeName": "OTROS",
                        "#text": "A-65232357"
                    }
                },
                "cac:PartyName": {
                    "cbc:Name": "ADAMO TELCOM IBERIA, SA"
                }
            },
            "cac:AwardedTenderedProject": {
                "cac:LegalMonetaryTotal": {
                    "cbc:TaxExclusiveAmount": {
                        "@currencyID": "EUR",
                        "#text": "6000"
                    }
                }
            }
        },
        "cac:TenderingProcess": {
            "cbc:ProcedureCode": {
                "@listURI": "https://contrataciondelestado.es/codice/cl/2.04/SyndicationTenderingProcessCode-2.04.gc",
                "#text": "3"
            }
        },
        "cac-place-ext:ValidNoticeInfo": [
            {
                "cbc-place-ext:NoticeTypeCode": {
                    "@listURI": "http://contrataciondelestado.es/codice/cl/2.04/TenderingNoticeTypeCode-2.04.gc",
                    "#text": "DOC_CAN_ADJ"
                },
                "cac-place-ext:AdditionalPublicationStatus": {
                    "cbc-place-ext:PublicationMediaName": "Perfil del contratante",
                    "cac-place-ext:AdditionalPublicationDocumentReference": {
                        "cbc:IssueDate": "2016-04-06"
                    }
                }
            },
            {
                "cbc-place-ext:NoticeTypeCode": {
                    "@listURI": "http://contrataciondelestado.es/codice/cl/2.04/TenderingNoticeTypeCode-2.04.gc",
                    "#text": "DOC_FORM"
                },
                "cac-place-ext:AdditionalPublicationStatus": {
                    "cbc-place-ext:PublicationMediaName": "Perfil del contratante",
                    "cac-place-ext:AdditionalPublicationDocumentReference": {
                        "cbc:IssueDate": "2016-07-29"
                    }
                }
            }
        ]
    }
}